Metadata-Version: 1.0
Name: libopeniot
Version: 0.3.1.3
Summary: OpenIoT Library
Home-page: http://www.openiot.org.ng
Author: Ahmad Sadiq
Author-email: sadiq.a.ahmad@gmail.com
License: BSD
Platform: UNKNOWN
